liteclient/__init__.py
liteclient/client.py
liteclient-0.1.0.dist-info/METADATA
liteclient-0.1.0.dist-info/WHEEL
liteclient-0.1.0.dist-info/entry_points.txt
liteclient-0.1.0.dist-info/RECORD
