Metadata-Version: 2.4
Name: liteclient
Version: 0.1.0
Summary: Add your description here
Author-email: Joe Pasquantonio <joe.pasquantonio@gmail.com>
Requires-Python: >=3.11
Requires-Dist: respparser>=0.1.0
